language_autoswitcher/__init__.py
language_autoswitcher/middleware.py
django_language_autoswitcher-0.0.2.dist-info/LICENSE
django_language_autoswitcher-0.0.2.dist-info/METADATA
django_language_autoswitcher-0.0.2.dist-info/WHEEL
django_language_autoswitcher-0.0.2.dist-info/top_level.txt
django_language_autoswitcher-0.0.2.dist-info/RECORD
